MANIFEST.in
README.md
setup.py
businessoptics/__init__.py
businessoptics/cached_file_getter.py
businessoptics/client.py
businessoptics/exceptions.py
businessoptics/google_drive.py
businessoptics/utils.py
businessoptics.egg-info/PKG-INFO
businessoptics.egg-info/SOURCES.txt
businessoptics.egg-info/dependency_links.txt
businessoptics.egg-info/not-zip-safe
businessoptics.egg-info/requires.txt
businessoptics.egg-info/top_level.txt