Metadata-Version: 2.1
Name: businessoptics
Version: 0.7.1
Summary: Client for the BusinessOptics API
Home-page: https://github.com/BusinessOptics/businessoptics_client
Author: BusinessOptics
Author-email: alex.mojaki@gmail.com
License: MIT
Platform: UNKNOWN
Classifier: License :: OSI Approved :: MIT License
Classifier: Programming Language :: Python :: 2.7
Classifier: Programming Language :: Python :: 3.5
